{
  "slug": "skolko-stoit-bankrotstvo-fizicheskogo-lica",
  "category": "fiz",
  "h1": "Сколько стоит банкротство физического лица: разбираем все расходы",
  "title": "Стоимость банкротства физлица в 2026 году",
  "description": "Из чего складывается цена банкротства физического лица: госпошлина, вознаграждение управляющего, публикации. Минимальная сумма - от 25 000 рублей.",
  "main_keyword": "сколько стоит банкротство физического лица",
  "frequency_estimate": null,
  "frequency_main": null,
  "frequency_secondary": null,
  "frequency_total": null,
  "frequency_checked_at": null,
  "frequency_region": null,
  "secondary_keywords": [
    "стоимость процедуры банкротства физлица",
    "расходы при банкротстве физического лица",
    "из чего складывается цена банкротства",
    "госпошлина при банкротстве физлица 2026",
    "вознаграждение финансового управляющего",
    "цена банкротства физического лица 2026",
    "внесудебное банкротство бесплатно",
    "судебное банкротство стоимость"
  ],
  "lsi": [
    "депозит арбитражного суда",
    "публикации в Федресурсе",
    "процедура реализации имущества",
    "реструктуризация долгов стоимость",
    "минимальные расходы банкротство",
    "юридическое сопровождение банкротства",
    "финансовый управляющий 25000 рублей",
    "банкротство через МФЦ цена",
    "списание долгов стоимость",
    "обязательные платежи при банкротстве"
  ],
  "intent": "commercial",
  "funnel_stage": "hot",
  "article_type": "B",
  "offer": "raschet-stoimosti",
  "cannibalization_check": "warn:cluster:fiz-bankruptcy-consequences",
  "event_date": null,
  "news_zone": null,
  "primary_source": null
}
