{
  "slug": "bankrotstvo-postavshchika-po-goskontraktu",
  "category": "yur",
  "h1": "Банкротство поставщика по госконтракту: что делать заказчику",
  "title": "Банкротство поставщика по госконтракту: права заказчика",
  "description": "Поставщик по 44-ФЗ признан банкротом: как расторгнуть контракт, вернуть аванс, включиться в реестр кредиторов и защитить интересы бюджетной организации.",
  "main_keyword": "банкротство поставщика по госконтракту",
  "frequency_estimate": null,
  "frequency_main": null,
  "frequency_secondary": null,
  "frequency_total": null,
  "frequency_checked_at": null,
  "frequency_region": null,
  "secondary_keywords": [
    "расторжение госконтракта при банкротстве поставщика",
    "права заказчика при банкротстве подрядчика",
    "включение в реестр кредиторов по госконтракту",
    "аванс по госконтракту при банкротстве",
    "реестр недобросовестных поставщиков при банкротстве",
    "что делать заказчику если поставщик банкрот",
    "одностороннее расторжение контракта банкротство"
  ],
  "lsi": [
    "44-ФЗ банкротство подрядчика",
    "конкурсное производство поставщик",
    "текущие платежи госконтракт",
    "арбитражный управляющий контракт",
    "ст. 95 44-ФЗ расторжение",
    "ст. 31 44-ФЗ требования участника",
    "ст. 104 44-ФЗ реестр недобросовестных",
    "обеспечение исполнения контракта",
    "банковская гарантия при банкротстве поставщика",
    "223-ФЗ банкротство поставщика"
  ],
  "intent": "informational",
  "funnel_stage": "warm",
  "article_type": "C",
  "offer": "snyatie-aresta",
  "cannibalization_check": "warn:postavshchik-pri-bankrotstve-pokupatelya"
}
