{
  "slug": "ustupka-prava-trebovaniya-pered-bankrotstvom",
  "category": "yur",
  "h1": "Уступка права требования перед банкротством: чем рискует цессионарий",
  "title": "Уступка права требования перед банкротством: риски",
  "description": "Чем грозит цессия, оформленная за год до банкротства должника: оспаривание по ст. 61.2-61.3 ФЗ-127, критерии подозрительности, позиция ВС и как снизить риски.",
  "main_keyword": "уступка права требования перед банкротством",
  "frequency_main": null,
  "frequency_secondary": null,
  "frequency_total": null,
  "frequency_checked_at": null,
  "frequency_region": null,
  "frequency_estimate": null,
  "secondary_keywords": [
    "оспаривание цессии при банкротстве",
    "договор цессии при банкротстве должника",
    "уступка требования подозрительная сделка",
    "цессия банкротство риски цессионария",
    "признание цессии недействительной банкротство",
    "цессия период подозрительности",
    "уступка долга до банкротства юридического лица"
  ],
  "lsi": [
    "статья 61.2 ФЗ-127",
    "статья 61.3 ФЗ-127",
    "неравноценное встречное исполнение",
    "период подозрительности",
    "арбитражный управляющий",
    "конкурсное производство",
    "реестр кредиторов",
    "сделка с предпочтением",
    "цедент цессионарий",
    "добросовестность цессионария",
    "Верховный суд практика цессия",
    "вывод активов банкротство"
  ],
  "intent": "informational",
  "funnel_stage": "warm",
  "article_type": "B",
  "offer": "raschet-stoimosti",
  "cannibalization_check": "ok"
}
